pyprind/__init__.py
pyprind/generator_factory.py
pyprind/prog_class.py
pyprind/progbar.py
pyprind/progpercent.py
PyPrind-2.11.3.dist-info/LICENSE
PyPrind-2.11.3.dist-info/METADATA
PyPrind-2.11.3.dist-info/WHEEL
PyPrind-2.11.3.dist-info/top_level.txt
PyPrind-2.11.3.dist-info/RECORD
