Metadata-Version: 1.1
Name: PyPrind
Version: 2.11.3
Summary: Python Progress Bar and Percent Indicator Utility
Home-page: https://github.com/rasbt/pyprind
Author: Sebastian Raschka
Author-email: mail@sebastianraschka.com
License: BSD 3-Clause
Platform: any
Classifier: License :: OSI Approved :: BSD License
Classifier: Development Status :: 5 - Production/Stable
Classifier: Programming Language :: Python :: 2.7
Classifier: Programming Language :: Python :: 3
Classifier: Environment :: Console
